md2mrkdwn/__init__.py
md2mrkdwn/converter.py
md2mrkdwn/patterns.py
md2mrkdwn-0.4.3.dist-info/METADATA
md2mrkdwn-0.4.3.dist-info/WHEEL
md2mrkdwn-0.4.3.dist-info/licenses/LICENSE
md2mrkdwn-0.4.3.dist-info/RECORD
