Metadata-Version: 2.4
Name: md2mrkdwn
Version: 0.4.3
Summary: Convert Markdown to Slack mrkdwn format
Project-URL: Homepage, https://github.com/bigbag/md2mrkdwn
Project-URL: Repository, https://github.com/bigbag/md2mrkdwn
Project-URL: Issues, https://github.com/bigbag/md2mrkdwn/issues
Author-email: Pavel Liashkov <pavel.liashkov@protonamil.com>
License-Expression: MIT
License-File: LICENSE
Keywords: converter,formatting,markdown,mrkdwn,slack
Classifier: Development Status :: 4 - Beta
Classifier: License :: OSI Approved :: MIT License
Classifier: Programming Language :: Python :: 3
Classifier: Programming Language :: Python :: 3.10
Classifier: Programming Language :: Python :: 3.11
Classifier: Programming Language :: Python :: 3.12
Classifier: Programming Language :: Python :: 3.13
Classifier: Programming Language :: Python :: 3.14
Classifier: Topic :: Communications :: Chat
Classifier: Topic :: Text Processing :: Markup
Requires-Python: >=3.10
Requires-Dist: wcwidth>=0.2.0
